myfunctions_danpuz7/__init__.py
myfunctions_danpuz7/math.py
myfunctions_danpuz7-0.0.2.dist-info/METADATA
myfunctions_danpuz7-0.0.2.dist-info/WHEEL
myfunctions_danpuz7-0.0.2.dist-info/top_level.txt
myfunctions_danpuz7-0.0.2.dist-info/RECORD
