Metadata-Version: 2.1
Name: myfunctions-danpuz7
Version: 0.0.2
Summary: A description of your package
Home-page: https://github.com/danpuz7
Author: Daniel Puzan
Author-email: danpuz7@gmail.com
License: MIT
Platform: UNKNOWN
Classifier: Programming Language :: Python :: 3
Classifier: License :: OSI Approved :: MIT License
Classifier: Operating System :: OS Independent
Requires-Python: >=3.6
